swimlane_python_logger/__init__.py
swimlane_python_logger/main.py
swimlane_python_logger-1.0.dist-info/METADATA
swimlane_python_logger-1.0.dist-info/RECORD
swimlane_python_logger-1.0.dist-info/WHEEL
swimlane_python_logger-1.0.dist-info/top_level.txt
