Metadata-Version: 2.1
Name: swimlane-python-logger
Version: 1.0
Summary: Logger wrapper class for Swimlane Integrations
Home-page: https://github.com/jeremymcrews/swimlane_python_logger
Author: Jeremy m Crews
Author-email: jeremy.m.crews@gmail.com
License: UNKNOWN
Platform: UNKNOWN
Classifier: Programming Language :: Python :: 2
Classifier: License :: OSI Approved :: MIT License
Classifier: Operating System :: OS Independent
